serializer_permissions/__init__.py
serializer_permissions/fields.py
serializer_permissions/mixins.py
serializer_permissions/relations.py
serializer_permissions/serializers.py
restframework_serializer_permissions-0.0.2.dist-info/LICENSE
restframework_serializer_permissions-0.0.2.dist-info/METADATA
restframework_serializer_permissions-0.0.2.dist-info/WHEEL
restframework_serializer_permissions-0.0.2.dist-info/top_level.txt
restframework_serializer_permissions-0.0.2.dist-info/RECORD
