Metadata-Version: 2.1
Name: restframework-serializer-permissions
Version: 0.0.2
Summary: permission based serializing for django restframework
Home-page: https://github.com/manfred-kaiser/restframework-serializer-permissions
Author: Manfred Kaiser
Author-email: manfred.kaiser@ssh-mitm.at
License: UNKNOWN
Platform: UNKNOWN
Classifier: Programming Language :: Python :: 3
Classifier: Environment :: Web Environment
Classifier: Framework :: Django
Classifier: Intended Audience :: Developers
Classifier: Operating System :: OS Independent
Classifier: Topic :: Internet :: WWW/HTTP
Classifier: Topic :: Internet :: WWW/HTTP :: Dynamic Content
Classifier: License :: OSI Approved :: GNU General Public License v3 (GPLv3)
